RulebaseProductionSystem/__init__.py
RulebaseProductionSystem/planner.py
RulebaseProductionSystem-0.1.3.dist-info/METADATA
RulebaseProductionSystem-0.1.3.dist-info/WHEEL
RulebaseProductionSystem-0.1.3.dist-info/top_level.txt
RulebaseProductionSystem-0.1.3.dist-info/RECORD
