Metadata-Version: 2.1
Name: RulebaseProductionSystem
Version: 0.1.3
Summary: A python library used to make plans using rulebase production system
Author: mughalfrazk
Author-email: <mughalfrazk@gmail.com>
